<archimate:ArchimateDiagramModel
    xmlns:xsi="http://www.w3.org/2001/XMLSchema-instance"
    xmlns:archimate="http://www.archimatetool.com/archimate"
    name="Ladok3 - Fundamental usage of RPC"
    id="71b9e76a"
    viewpoint="13">
  <children
      xsi:type="archimate:DiagramModelArchimateObject"
      id="80640c36"
      targetConnections="a00ef8bf">
    <sourceConnections
        xsi:type="archimate:DiagramModelArchimateConnection"
        id="8b053c5f"
        source="80640c36"
        target="6edd335d">
      <archimateRelationship
          xsi:type="archimate:FlowRelationship"
          href="FlowRelationship_069f7973.xml#069f7973"/>
    </sourceConnections>
    <sourceConnections
        xsi:type="archimate:DiagramModelArchimateConnection"
        id="3d53c127"
        source="80640c36"
        target="9a9df844">
      <archimateRelationship
          xsi:type="archimate:SpecializationRelationship"
          href="SpecializationRelationship_3406a1fb.xml#3406a1fb"/>
    </sourceConnections>
    <bounds
        x="167"
        y="108"
        width="120"
        height="55"/>
    <archimateElement
        xsi:type="archimate:TechnologyService"
        href="TechnologyService_db2619d5.xml#db2619d5"/>
  </children>
  <children
      xsi:type="archimate:DiagramModelArchimateObject"
      id="3bd7e715"
      targetConnections="ee817253 2120091f">
    <bounds
        x="396"
        y="252"
        width="120"
        height="55"/>
    <archimateElement
        xsi:type="archimate:TechnologyInterface"
        href="TechnologyInterface_767cdce4.xml#767cdce4"/>
  </children>
  <children
      xsi:type="archimate:DiagramModelArchimateObject"
      id="3903432e">
    <sourceConnections
        xsi:type="archimate:DiagramModelArchimateConnection"
        id="ee817253"
        source="3903432e"
        target="3bd7e715">
      <archimateRelationship
          xsi:type="archimate:CompositionRelationship"
          href="CompositionRelationship_7da44fd2.xml#7da44fd2"/>
    </sourceConnections>
    <sourceConnections
        xsi:type="archimate:DiagramModelArchimateConnection"
        id="a00ef8bf"
        source="3903432e"
        target="80640c36">
      <archimateRelationship
          xsi:type="archimate:RealizationRelationship"
          href="RealizationRelationship_acdb68c4.xml#acdb68c4"/>
    </sourceConnections>
    <sourceConnections
        xsi:type="archimate:DiagramModelArchimateConnection"
        id="d2e92777"
        source="3903432e"
        target="b22433fd">
      <archimateRelationship
          xsi:type="archimate:AccessRelationship"
          href="AccessRelationship_c3f3c994.xml#c3f3c994"/>
    </sourceConnections>
    <bounds
        x="132"
        y="192"
        width="191"
        height="481"/>
    <archimateElement
        xsi:type="archimate:Node"
        href="Node_72362159.xml#72362159"/>
  </children>
  <children
      xsi:type="archimate:DiagramModelArchimateObject"
      id="32fd3d56"
      targetConnections="ae36b80f">
    <bounds
        x="396"
        y="618"
        width="120"
        height="55"/>
    <archimateElement
        xsi:type="archimate:Artifact"
        href="Artifact_c21366bb.xml#c21366bb"/>
  </children>
  <children
      xsi:type="archimate:DiagramModelArchimateObject"
      id="21c7bf83">
    <sourceConnections
        xsi:type="archimate:DiagramModelArchimateConnection"
        id="2120091f"
        source="21c7bf83"
        target="3bd7e715">
      <archimateRelationship
          xsi:type="archimate:ServingRelationship"
          href="ServingRelationship_5a22a9a6.xml#5a22a9a6"/>
    </sourceConnections>
    <sourceConnections
        xsi:type="archimate:DiagramModelArchimateConnection"
        id="e78d052a"
        source="21c7bf83"
        target="cbb8939a">
      <archimateRelationship
          xsi:type="archimate:AssignmentRelationship"
          href="AssignmentRelationship_0d7dd0e3.xml#0d7dd0e3"/>
    </sourceConnections>
    <sourceConnections
        xsi:type="archimate:DiagramModelArchimateConnection"
        id="febd3ed5"
        source="21c7bf83"
        target="b22433fd">
      <archimateRelationship
          xsi:type="archimate:AccessRelationship"
          href="AccessRelationship_7d532d9b.xml#7d532d9b"/>
    </sourceConnections>
    <bounds
        x="612"
        y="193"
        width="456"
        height="480"/>
    <children
        xsi:type="archimate:DiagramModelArchimateObject"
        id="5d4741df">
      <sourceConnections
          xsi:type="archimate:DiagramModelArchimateConnection"
          id="7824a4aa"
          source="5d4741df"
          target="74a4e108">
        <archimateRelationship
            xsi:type="archimate:AssignmentRelationship"
            href="AssignmentRelationship_6f5987bb.xml#6f5987bb"/>
      </sourceConnections>
      <bounds
          x="239"
          y="372"
          width="169"
          height="55"/>
      <archimateElement
          xsi:type="archimate:SystemSoftware"
          href="SystemSoftware_3b880fe0.xml#3b880fe0"/>
    </children>
    <children
        xsi:type="archimate:DiagramModelGroup"
        id="63ce5f38"
        name="Common Code Library">
      <bounds
          x="11"
          y="126"
          width="421"
          height="97"/>
    </children>
    <children
        xsi:type="archimate:DiagramModelArchimateObject"
        id="d5f17215"
        targetConnections="70bde508">
      <sourceConnections
          xsi:type="archimate:DiagramModelArchimateConnection"
          id="05c2ccf6"
          source="d5f17215"
          target="71b45a49">
        <archimateRelationship
            xsi:type="archimate:AssociationRelationship"
            href="AssociationRelationship_fcc03614.xml#fcc03614"/>
      </sourceConnections>
      <bounds
          x="240"
          y="156"
          width="168"
          height="55"/>
      <archimateElement
          xsi:type="archimate:TechnologyFunction"
          href="TechnologyFunction_ffccaa42.xml#ffccaa42"/>
    </children>
    <children
        xsi:type="archimate:DiagramModelArchimateObject"
        id="74a4e108"
        targetConnections="7824a4aa">
      <sourceConnections
          xsi:type="archimate:DiagramModelArchimateConnection"
          id="70bde508"
          source="74a4e108"
          target="d5f17215">
        <archimateRelationship
            xsi:type="archimate:ServingRelationship"
            href="ServingRelationship_c384e982.xml#c384e982"/>
      </sourceConnections>
      <sourceConnections
          xsi:type="archimate:DiagramModelArchimateConnection"
          id="293052bd"
          source="74a4e108"
          target="71b45a49">
        <archimateRelationship
            xsi:type="archimate:ServingRelationship"
            href="ServingRelationship_bc60c49a.xml#bc60c49a"/>
      </sourceConnections>
      <bounds
          x="240"
          y="276"
          width="168"
          height="55"/>
      <archimateElement
          xsi:type="archimate:TechnologyFunction"
          href="TechnologyFunction_fe36d041.xml#fe36d041"/>
    </children>
    <children
        xsi:type="archimate:DiagramModelArchimateObject"
        id="71b45a49"
        targetConnections="293052bd 05c2ccf6">
      <sourceConnections
          xsi:type="archimate:DiagramModelArchimateConnection"
          id="7032c838"
          source="71b45a49"
          target="6edd335d">
        <archimateRelationship
            xsi:type="archimate:RealizationRelationship"
            href="RealizationRelationship_46e79002.xml#46e79002"/>
      </sourceConnections>
      <sourceConnections
          xsi:type="archimate:DiagramModelArchimateConnection"
          id="f786324c"
          source="71b45a49"
          target="cbb8939a">
        <archimateRelationship
            xsi:type="archimate:SpecializationRelationship"
            href="SpecializationRelationship_e431fe4f.xml#e431fe4f"/>
      </sourceConnections>
      <bounds
          x="36"
          y="156"
          width="168"
          height="55"/>
      <archimateElement
          xsi:type="archimate:TechnologyFunction"
          href="TechnologyFunction_db6730e2.xml#db6730e2"/>
    </children>
    <children
        xsi:type="archimate:DiagramModelArchimateObject"
        id="cbb8939a"
        targetConnections="e78d052a f786324c">
      <bounds
          x="240"
          y="60"
          width="168"
          height="55"/>
      <archimateElement
          xsi:type="archimate:TechnologyFunction"
          href="TechnologyFunction_e66a2cd4.xml#e66a2cd4"/>
    </children>
    <archimateElement
        xsi:type="archimate:Node"
        href="Node_12aecc73.xml#12aecc73"/>
  </children>
  <children
      xsi:type="archimate:DiagramModelArchimateObject"
      id="6edd335d"
      targetConnections="8b053c5f 7032c838">
    <sourceConnections
        xsi:type="archimate:DiagramModelArchimateConnection"
        id="19b359a2"
        source="6edd335d"
        target="7fb9a210">
      <archimateRelationship
          xsi:type="archimate:SpecializationRelationship"
          href="SpecializationRelationship_57a5c01b.xml#57a5c01b"/>
    </sourceConnections>
    <bounds
        x="648"
        y="108"
        width="168"
        height="55"/>
    <archimateElement
        xsi:type="archimate:TechnologyService"
        href="TechnologyService_5a38d416.xml#5a38d416"/>
  </children>
  <children
      xsi:type="archimate:DiagramModelArchimateObject"
      id="7fb9a210"
      targetConnections="19b359a2">
    <bounds
        x="648"
        y="24"
        width="168"
        height="55"/>
    <archimateElement
        xsi:type="archimate:TechnologyService"
        href="TechnologyService_4b4b69f3.xml#4b4b69f3"/>
  </children>
  <children
      xsi:type="archimate:DiagramModelArchimateObject"
      id="b22433fd"
      targetConnections="d2e92777 febd3ed5">
    <sourceConnections
        xsi:type="archimate:DiagramModelArchimateConnection"
        id="ae36b80f"
        source="b22433fd"
        target="32fd3d56">
      <archimateRelationship
          xsi:type="archimate:SpecializationRelationship"
          href="SpecializationRelationship_49dadd43.xml#49dadd43"/>
    </sourceConnections>
    <bounds
        x="396"
        y="468"
        width="120"
        height="55"/>
    <archimateElement
        xsi:type="archimate:Artifact"
        href="Artifact_d2139cca.xml#d2139cca"/>
  </children>
  <children
      xsi:type="archimate:DiagramModelArchimateObject"
      id="9a9df844"
      targetConnections="3d53c127">
    <bounds
        x="166"
        y="24"
        width="120"
        height="55"/>
    <archimateElement
        xsi:type="archimate:TechnologyService"
        href="TechnologyService_b5ea9d5f.xml#b5ea9d5f"/>
  </children>
</archimate:ArchimateDiagramModel>
