<archimate:ArchimateDiagramModel
    xmlns:xsi="http://www.w3.org/2001/XMLSchema-instance"
    xmlns:archimate="http://www.archimatetool.com/archimate"
    name="Processer kopplade till aktörer, roller och tjänster"
    id="ba59a937">
  <children
      xsi:type="archimate:DiagramModelArchimateObject"
      id="5d815b02"
      targetConnections="e4e7d48f"
      textPosition="1"
      type="1">
    <sourceConnections
        id="a617330f"
        source="5d815b02"
        target="1bc3f77f"/>
    <bounds
        x="108"
        y="192"
        width="193"
        height="85"/>
    <archimateElement
        xsi:type="archimate:BusinessProcess"
        href="BusinessProcess_d6ed5e55.xml#d6ed5e55"/>
  </children>
  <children
      xsi:type="archimate:DiagramModelArchimateObject"
      id="cc3c6529"
      textPosition="1"
      type="1">
    <sourceConnections
        xsi:type="archimate:DiagramModelArchimateConnection"
        id="f498e549"
        source="cc3c6529"
        target="45fe03ed">
      <archimateRelationship
          xsi:type="archimate:AssociationRelationship"
          href="AssociationRelationship_d969ded6.xml#d969ded6"/>
    </sourceConnections>
    <sourceConnections
        id="9e0975a8"
        source="cc3c6529"
        target="1bc3f77f"/>
    <bounds
        x="276"
        y="288"
        width="193"
        height="85"/>
    <archimateElement
        xsi:type="archimate:BusinessProcess"
        href="BusinessProcess_91c9e508.xml#91c9e508"/>
  </children>
  <children
      xsi:type="archimate:DiagramModelArchimateObject"
      id="b21dbd0e"
      textPosition="1"
      type="1">
    <sourceConnections
        xsi:type="archimate:DiagramModelArchimateConnection"
        id="912e4733"
        source="b21dbd0e"
        target="52bd749f">
      <archimateRelationship
          xsi:type="archimate:AssociationRelationship"
          href="AssociationRelationship_1fd22d2e.xml#1fd22d2e"/>
    </sourceConnections>
    <sourceConnections
        xsi:type="archimate:DiagramModelArchimateConnection"
        id="567e7018"
        source="b21dbd0e"
        target="571de8aa">
      <archimateRelationship
          xsi:type="archimate:AssociationRelationship"
          href="AssociationRelationship_2bc2ef77.xml#2bc2ef77"/>
    </sourceConnections>
    <bounds
        x="456"
        y="216"
        width="193"
        height="85"/>
    <archimateElement
        xsi:type="archimate:BusinessProcess"
        href="BusinessProcess_6b74e5b1.xml#6b74e5b1"/>
  </children>
  <children
      xsi:type="archimate:DiagramModelArchimateObject"
      id="00ac2240"
      targetConnections="9ea1cde2 46a186d9 a3ab71c5 b73e5fa7-b315-4770-a989-861259e866f5"
      textPosition="1"
      type="1">
    <sourceConnections
        xsi:type="archimate:DiagramModelArchimateConnection"
        id="0d71d9c5"
        source="00ac2240"
        target="474523aa">
      <bendpoints
          startY="-78"
          endX="-96"
          endY="57"/>
      <archimateRelationship
          xsi:type="archimate:AssociationRelationship"
          href="AssociationRelationship_8ca9153b.xml#8ca9153b"/>
    </sourceConnections>
    <bounds
        x="732"
        y="192"
        width="252"
        height="85"/>
    <archimateElement
        xsi:type="archimate:BusinessProcess"
        href="BusinessProcess_d9692412.xml#d9692412"/>
  </children>
  <children
      xsi:type="archimate:DiagramModelArchimateObject"
      id="e322edc0"
      textPosition="1"
      type="1">
    <sourceConnections
        xsi:type="archimate:DiagramModelArchimateConnection"
        id="9ea1cde2"
        source="e322edc0"
        target="00ac2240">
      <archimateRelationship
          xsi:type="archimate:SpecializationRelationship"
          href="SpecializationRelationship_27f4e0b5.xml#27f4e0b5"/>
    </sourceConnections>
    <bounds
        x="612"
        y="324"
        width="193"
        height="85"/>
    <archimateElement
        xsi:type="archimate:BusinessProcess"
        href="BusinessProcess_8c65ee64.xml#8c65ee64"/>
  </children>
  <children
      xsi:type="archimate:DiagramModelArchimateObject"
      id="a5eecdc9"
      textPosition="1"
      type="1">
    <sourceConnections
        xsi:type="archimate:DiagramModelArchimateConnection"
        id="b73e5fa7-b315-4770-a989-861259e866f5"
        source="a5eecdc9"
        target="00ac2240">
      <archimateRelationship
          xsi:type="archimate:SpecializationRelationship"
          href="SpecializationRelationship_fff73900-38fe-4dcd-8bcb-2479edb47626.xml#fff73900-38fe-4dcd-8bcb-2479edb47626"/>
    </sourceConnections>
    <bounds
        x="912"
        y="324"
        width="193"
        height="85"/>
    <archimateElement
        xsi:type="archimate:BusinessProcess"
        href="BusinessProcess_3924d33c.xml#3924d33c"/>
  </children>
  <children
      xsi:type="archimate:DiagramModelArchimateObject"
      id="45fe03ed"
      targetConnections="f498e549">
    <sourceConnections
        xsi:type="archimate:DiagramModelArchimateConnection"
        id="e4e7d48f"
        source="45fe03ed"
        target="5d815b02">
      <archimateRelationship
          xsi:type="archimate:AssociationRelationship"
          href="AssociationRelationship_e5d33d7c.xml#e5d33d7c"/>
    </sourceConnections>
    <bounds
        x="240"
        y="72"
        width="120"
        height="55"/>
    <archimateElement
        xsi:type="archimate:BusinessActor"
        href="BusinessActor_79d5712f.xml#79d5712f"/>
  </children>
  <children
      xsi:type="archimate:DiagramModelArchimateObject"
      id="474523aa"
      targetConnections="0d71d9c5">
    <bounds
        x="949"
        y="72"
        width="120"
        height="55"/>
    <archimateElement
        xsi:type="archimate:BusinessRole"
        href="BusinessRole_de2eaa71.xml#de2eaa71"/>
  </children>
  <children
      xsi:type="archimate:DiagramModelArchimateObject"
      id="52bd749f"
      targetConnections="912e4733"
      type="1">
    <bounds
        x="456"
        y="72"
        width="120"
        height="55"/>
    <archimateElement
        xsi:type="archimate:BusinessService"
        href="BusinessService_be6d775d.xml#be6d775d"/>
  </children>
  <children
      xsi:type="archimate:DiagramModelArchimateObject"
      id="571de8aa"
      targetConnections="567e7018">
    <sourceConnections
        xsi:type="archimate:DiagramModelArchimateConnection"
        id="a3ab71c5"
        source="571de8aa"
        target="00ac2240">
      <bendpoints
          startX="120"
          startY="57"
          endX="-60"
          endY="-78"/>
      <archimateRelationship
          xsi:type="archimate:AssociationRelationship"
          href="AssociationRelationship_48aa43bf.xml#48aa43bf"/>
    </sourceConnections>
    <bounds
        x="588"
        y="72"
        width="120"
        height="55"/>
    <archimateElement
        xsi:type="archimate:BusinessRole"
        href="BusinessRole_8dce3cbf.xml#8dce3cbf"/>
  </children>
  <children
      xsi:type="archimate:DiagramModelArchimateObject"
      id="b138895e"
      textPosition="1"
      type="1">
    <sourceConnections
        xsi:type="archimate:DiagramModelArchimateConnection"
        id="46a186d9"
        source="b138895e"
        target="00ac2240">
      <archimateRelationship
          xsi:type="archimate:SpecializationRelationship"
          href="SpecializationRelationship_05a07fd8.xml#05a07fd8"/>
    </sourceConnections>
    <bounds
        x="761"
        y="420"
        width="193"
        height="85"/>
    <archimateElement
        xsi:type="archimate:BusinessProcess"
        href="BusinessProcess_83339456.xml#83339456"/>
  </children>
  <children
      xsi:type="archimate:DiagramModelNote"
      id="1bc3f77f"
      targetConnections="a617330f 9e0975a8"
      textAlignment="1"
      content="Hanteras inte av lärosätet i paradigm 3 men lärosätena måste ändå ställa krav på processerna. I paradigm 1 och 2 kontrolleras och hanteras processerna av lärosätet.">
    <bounds
        x="12"
        y="291"
        width="185"
        height="130"/>
  </children>
  <children
      xsi:type="archimate:DiagramModelNote"
      id="a424e385-5c03-4d45-b800-9cd44937d253"
      textAlignment="1"
      content="Kvar att göra:&#xA; - vi har inte modellerat livscykelperspektivet&#xA; - vi behöver modelllera ett UC för automatiskt tilldelad behörighet&#xA; - analysera vårt applikationslager ur ett centralt/lokalt perspektiv&#xA; - väva in olika användningsområden (nätinloggning, webbtjänster, datorinloggningar etc.)&#xA;&#xA;&#xA;Har vi hanterat ">
    <bounds
        x="288"
        y="504"
        width="481"
        height="217"/>
  </children>
</archimate:ArchimateDiagramModel>
